amiya/__init__.py
amiya/amiya.py
amiya/apps_manager/__init__.py
amiya/apps_manager/app.py
amiya/apps_manager/apps_manager.py
amiya/apps_manager/apps_viewer.py
amiya/apps_manager/safety_monitor.py
amiya/apps_manager/test.py
amiya/apps_manager/sync_controller/__init__.py
amiya/apps_manager/sync_controller/sync_controller.py
amiya/apps_manager/sync_controller/sys_uuid_controller.py
amiya/automation_handler/__init__.py
amiya/automation_handler/automation_config_handler.py
amiya/automation_handler/automation_controller.py
amiya/automation_handler/automation_recorder.py
amiya/automation_handler/automation_viewer.py
amiya/automation_handler/units/__init__.py
amiya/automation_handler/units/action.py
amiya/automation_handler/units/plate.py
amiya/automation_handler/units/sequence.py
amiya/bin/focus_pid.exe
amiya/bin/get_active_pid.exe
amiya/bin/get_window_size.exe
amiya/bin/scripts/focus_pid.c
amiya/bin/scripts/get_active_pid.c
amiya/bin/scripts/get_window_size.c
amiya/entrypoints/__init__.py
amiya/entrypoints/entrypoint_handler.py
amiya/entrypoints/entrypoints.py
amiya/entrypoints/help_format_handler.py
amiya/exceptions/__init__.py
amiya/exceptions/exceptions.py
amiya/module_utilities/__init__.py
amiya/module_utilities/continuous_click_controller.py
amiya/module_utilities/cursor_controller.py
amiya/module_utilities/dev_features.py
amiya/module_utilities/power_controller.py
amiya/module_utilities/search_controller.py
amiya/module_utilities/url_tracker.py
amiya/module_utilities/volume_controller.py
amiya/pixel_calculator/__init__.py
amiya/pixel_calculator/pixel_calculator.py
amiya/pixel_calculator/resolution_detector.py
amiya/resources/amiya-cli-2.png
amiya/resources/amiya-cli-3.png
amiya/resources/amiya-cli-4.png
amiya/resources/amiya-cli.png
amiya/resources/amiya.png
amiya/resources/amiya_with_border.png
amiya/resources/code_snippets/add-app.png
amiya/resources/code_snippets/add-tag.png
amiya/resources/code_snippets/start.png
amiya/scheduler/__init__.py
amiya-0.0.4.dist-info/LICENSE
amiya-0.0.4.dist-info/METADATA
amiya-0.0.4.dist-info/WHEEL
amiya-0.0.4.dist-info/entry_points.txt
amiya-0.0.4.dist-info/top_level.txt
amiya-0.0.4.dist-info/RECORD
