Metadata-Version: 2.1
Name: amiya
Version: 0.0.4
Summary: A lightweight cross-platform automation tool for games and daily tasks!
Home-page: http://github.com/rezeroe/amiya
Author: Kevin L.
Author-email: kevinliu@vt.edu
Classifier: Programming Language :: Python :: 3
Classifier: License :: OSI Approved :: MIT License
Classifier: Operating System :: OS Independent
Classifier: Development Status :: 4 - Beta
Requires-Python: >=3.6, <4
License-File: LICENSE
Requires-Dist: pywin32
Requires-Dist: psutil
Requires-Dist: pynput
Requires-Dist: pyautogui
Requires-Dist: tabulate
Requires-Dist: setuptools
Requires-Dist: elevate
Requires-Dist: termcolor
Requires-Dist: schedule
Requires-Dist: screeninfo
Requires-Dist: customtkinter
Requires-Dist: pycaw
Requires-Dist: Pillow
